kissbt/__init__.py
kissbt/analyzer.py
kissbt/broker.py
kissbt/engine.py
kissbt/entities.py
kissbt/strategy.py
kissbt-0.1.5.dist-info/LICENSE
kissbt-0.1.5.dist-info/METADATA
kissbt-0.1.5.dist-info/WHEEL
kissbt-0.1.5.dist-info/top_level.txt
kissbt-0.1.5.dist-info/RECORD
