Metadata-Version: 2.2
Name: kissbt
Version: 0.1.5
Summary: The keep it simple backtesting framework for Python.
Author-email: Adrian Hasse <adrian.hasse@finblobs.com>
Maintainer-email: Adrian Hasse <adrian.hasse@finblobs.com>
License:                                  Apache License
Project-URL: homepage, https://github.com/FinBlobs/kissbt
Project-URL: bug-tracker, https://github.com/FinBlobs/kissbt/issues
Classifier: Programming Language :: Python :: 3
Classifier: License :: OSI Approved :: Apache Software License
Classifier: Operating System :: OS Independent
Requires-Python: >=3.10
License-File: LICENSE
Requires-Dist: numpy
Requires-Dist: pandas
Requires-Dist: matplotlib
Provides-Extra: dev
Requires-Dist: pytest; extra == "dev"
Requires-Dist: pytest-mock; extra == "dev"
Requires-Dist: flake8; extra == "dev"
Requires-Dist: black; extra == "dev"
Requires-Dist: isort; extra == "dev"
Requires-Dist: yfinance; extra == "dev"
Requires-Dist: pyarrow; extra == "dev"
